openai_cost_calculator/__init__.py
openai_cost_calculator/core.py
openai_cost_calculator/estimate.py
openai_cost_calculator/parser.py
openai_cost_calculator/pricing.py
openai_cost_calculator/runner_langchain.py
openai_cost_calculator/types.py
openai_cost_calculator_with_lanchain-1.0.0.dist-info/licenses/LICENSE
openai_cost_calculator_with_lanchain-1.0.0.dist-info/METADATA
openai_cost_calculator_with_lanchain-1.0.0.dist-info/WHEEL
openai_cost_calculator_with_lanchain-1.0.0.dist-info/top_level.txt
openai_cost_calculator_with_lanchain-1.0.0.dist-info/RECORD
