Metadata-Version: 2.4
Name: openai_cost_calculator_with_lanchain
Version: 1.0.0
Summary: A library to estimate OpenAI API costs based on token usage, integrating with Langchain. This is a fork from v1.1.1 of openai_cost_calculator by Orkun Kınay and Murat Barkın Kınay (https://github.com/orkunkinay/openai_cost_calculator).
Author: Marco Pennacchiotti (forked from openai_cost_calculator by Orkun Kınay and Murat Barkın Kınay)
Classifier: Programming Language :: Python :: 3
Classifier: Operating System :: OS Independent
Requires-Python: >=3.8.1
License-File: LICENSE
Requires-Dist: langchain>=0.0.27
Requires-Dist: langchain-openai>=0.1.25
Requires-Dist: python-dotenv>=1.0.1
Requires-Dist: requests>=2.32.4
Dynamic: license-file
